joint_metrics/__init__.py
joint_metrics/graph_metrics.py
test_package_fmri_dmri-0.0.2.dist-info/licenses/LICENSE
test_package_fmri_dmri-0.0.2.dist-info/METADATA
test_package_fmri_dmri-0.0.2.dist-info/WHEEL
test_package_fmri_dmri-0.0.2.dist-info/top_level.txt
test_package_fmri_dmri-0.0.2.dist-info/RECORD
