Metadata-Version: 2.4
Name: test-package-fMRI-dMRI
Version: 0.0.2
Summary: Implementation of joint dMRI and fMRI metrics
Author-email: Sam Williams <s.willowmalak@gmail.com>
License-Expression: GPL-3.0-only
Project-URL: GitHub, https://github.com/WILLOWMALAK/test_package.git
Keywords: joint metrics
Classifier: Intended Audience :: Science/Research
Classifier: Natural Language :: English
Classifier: Programming Language :: Python
License-File: LICENSE
Requires-Dist: numpy
Requires-Dist: networkx
Dynamic: license-file
